{"cameraMode":{"drawMode":0,"name":"Shaded","section":"Shading Mode"},"sceneLighting":false,"audioPlay":false,"sceneViewState":{"m_AlwaysRefresh":false,"showFog":true,"showSkybox":false,"showFlares":true,"showImageEffects":true,"showParticleSystems":true,"showVisualEffectGraphs":true,"m_FxEnabled":true},"in2DMode":false,"pivot":{"x":-1.9495173692703248,"y":-0.8526543378829956,"z":1.904832363128662},"rotation":{"x":0.20095723867416383,"y":-0.6515808701515198,"z":0.18495549261569978,"w":0.7078632116317749},"size":1.3597723245620728,"orthographic":false}